t5html/__init__.py
t5html/__main__.py
t5html/elementparser.py
t5html/importer.py
t5html/lineparser.py
t5html/treebuilder.py
t5html-23.6.2.dist-info/METADATA
t5html-23.6.2.dist-info/WHEEL
t5html-23.6.2.dist-info/entry_points.txt
t5html-23.6.2.dist-info/RECORD
