Metadata-Version: 2.1
Name: t5html
Version: 23.6.2
Summary: Converts text to html. Text muste be in t5html form.
Project-URL: Homepage, https://github.com/Exsplendor/t5html
Project-URL: Bug Tracker, https://github.com/Exsplendor/t5html/issues
Author-email: splendor <splendor@tuta.io>
Keywords: html,html5,template,templating,web
Classifier: Development Status :: 4 - Beta
Classifier: License :: OSI Approved :: MIT License
Classifier: Operating System :: OS Independent
Classifier: Programming Language :: Python :: 3
Classifier: Topic :: Text Processing :: Markup :: HTML
Requires-Python: >=3.8
